anime_muxer/__init__.py
anime_muxer/cli.py
anime_muxer/muxer.py
animux/__init__.py
animux/core.py
animux/main.py
animux/utils.py
animux-1.0.2.dist-info/METADATA
animux-1.0.2.dist-info/WHEEL
animux-1.0.2.dist-info/entry_points.txt
animux-1.0.2.dist-info/top_level.txt
animux-1.0.2.dist-info/RECORD
