Metadata-Version: 2.4
Name: animux
Version: 1.0.2
Summary: A professional Python library to mux different anime versions into a single MKV file.
Author-email: Tim Faul <tim.faul@yezun.de>
Classifier: Programming Language :: Python :: 3
Classifier: License :: OSI Approved :: MIT License
Classifier: Operating System :: OS Independent
Requires-Python: >=3.8
Requires-Dist: click
Requires-Dist: rich
Requires-Dist: subliminal
Requires-Dist: ffsubsync
